{"frames": {

"FractureCharacter.png":
{
	"frame": {"x":0,"y":0,"w":400,"h":200},
	"rotated": false,
	"trimmed": false,
	"spriteSourceSize": {"x":0,"y":0,"w":400,"h":200},
	"sourceSize": {"w":400,"h":200}
},
"FractureCharacterFlipped.png":
{
	"frame": {"x":403,"y":0,"w":400,"h":200},
	"rotated": false,
	"trimmed": false,
	"spriteSourceSize": {"x":0,"y":0,"w":400,"h":200},
	"sourceSize": {"w":400,"h":200}
},
"PalmreaderCharacter.png":
{
	"frame": {"x":806,"y":0,"w":400,"h":200},
	"rotated": false,
	"trimmed": false,
	"spriteSourceSize": {"x":0,"y":0,"w":400,"h":200},
	"sourceSize": {"w":400,"h":200}
},
"PalmreaderCharacterFlipped.png":
{
	"frame": {"x":1209,"y":0,"w":400,"h":200},
	"rotated": false,
	"trimmed": false,
	"spriteSourceSize": {"x":0,"y":0,"w":400,"h":200},
	"sourceSize": {"w":400,"h":200}
},
"ProBonoFractureCharacter.png":
{
	"frame": {"x":1612,"y":0,"w":400,"h":200},
	"rotated": false,
	"trimmed": false,
	"spriteSourceSize": {"x":0,"y":0,"w":400,"h":200},
	"sourceSize": {"w":400,"h":200}
},
"ProBonoFractureCharacterFlipped.png":
{
	"frame": {"x":0,"y":203,"w":400,"h":200},
	"rotated": false,
	"trimmed": false,
	"spriteSourceSize": {"x":0,"y":0,"w":400,"h":200},
	"sourceSize": {"w":400,"h":200}
},
"TheGoalieCharacter.png":
{
	"frame": {"x":403,"y":203,"w":400,"h":200},
	"rotated": false,
	"trimmed": false,
	"spriteSourceSize": {"x":0,"y":0,"w":400,"h":200},
	"sourceSize": {"w":400,"h":200}
},
"TheGoalieCharacterFlipped.png":
{
	"frame": {"x":806,"y":203,"w":400,"h":200},
	"rotated": false,
	"trimmed": false,
	"spriteSourceSize": {"x":0,"y":0,"w":400,"h":200},
	"sourceSize": {"w":400,"h":200}
},
"TheGoalieOnIceCharacter.png":
{
	"frame": {"x":1209,"y":203,"w":400,"h":200},
	"rotated": false,
	"trimmed": false,
	"spriteSourceSize": {"x":0,"y":0,"w":400,"h":200},
	"sourceSize": {"w":400,"h":200}
},
"TheGoalieOnIceCharacterFlipped.png":
{
	"frame": {"x":1612,"y":203,"w":400,"h":200},
	"rotated": false,
	"trimmed": false,
	"spriteSourceSize": {"x":0,"y":0,"w":400,"h":200},
	"sourceSize": {"w":400,"h":200}
},
"TorrentCharacter.png":
{
	"frame": {"x":0,"y":406,"w":400,"h":200},
	"rotated": false,
	"trimmed": false,
	"spriteSourceSize": {"x":0,"y":0,"w":400,"h":200},
	"sourceSize": {"w":400,"h":200}
},
"TorrentCharacterFlipped.png":
{
	"frame": {"x":403,"y":406,"w":400,"h":200},
	"rotated": false,
	"trimmed": false,
	"spriteSourceSize": {"x":0,"y":0,"w":400,"h":200},
	"sourceSize": {"w":400,"h":200}
},
"TorrentDenialOfServiceCharacter.png":
{
	"frame": {"x":806,"y":406,"w":400,"h":200},
	"rotated": false,
	"trimmed": false,
	"spriteSourceSize": {"x":0,"y":0,"w":400,"h":200},
	"sourceSize": {"w":400,"h":200}
},
"TorrentDenialOfServiceCharacterFlipped.png":
{
	"frame": {"x":1209,"y":406,"w":400,"h":200},
	"rotated": false,
	"trimmed": false,
	"spriteSourceSize": {"x":0,"y":0,"w":400,"h":200},
	"sourceSize": {"w":400,"h":200}
}},
"meta": {
	"app": "https://www.codeandweb.com/texturepacker",
	"version": "1.0",
	"image": "EndGameHeroes0.png",
	"format": "RGBA8888",
	"size": {"w":2048,"h":2048},
	"scale": "1",
	"smartupdate": "$TexturePacker:SmartUpdate:d7bb37f6141837832216bfa65c8ab96d:120939f1db7b1b64bf95c4c766f8b1cf:e92652cff04ed6c8e37f7bc0458ec814$"
}
}
